{
    "airports": [
        { "active": "False", "heatmap": 0, "icao": "null", "led": "0", "purpose": "off", "wxsrc": "none" },
        { "active": "False", "heatmap": 0, "icao": "null", "led": "1", "purpose": "off", "wxsrc": "none" },
        { "active": "False", "heatmap": 0, "icao": "null", "led": "2", "purpose": "off", "wxsrc": "none" },
        { "active": "False", "heatmap": 0, "icao": "null", "led": "3", "purpose": "off", "wxsrc": "none" },
        { "active": "False", "heatmap": 0, "icao": "null", "led": "4", "purpose": "off", "wxsrc": "none" },
        { "active": "False", "heatmap": 0, "icao": "null", "led": "5", "purpose": "off", "wxsrc": "none" },
        { "active": "True", "heatmap": 0, "icao": "kplu", "led": "6", "purpose": "all", "wxsrc": "adds" },
        { "active": "True", "heatmap": 0, "icao": "ktcm", "led": "7", "purpose": "all", "wxsrc": "adds" },
        { "active": "True", "heatmap": 0, "icao": "kgrf", "led": "8", "purpose": "all", "wxsrc": "adds" },
        { "active": "True", "heatmap": 1, "icao": "kolm", "led": "9", "purpose": "all", "wxsrc": "adds" },
        { "active": "True", "heatmap": 10, "icao": "kshn", "led": "10", "purpose": "all", "wxsrc": "adds" },
        { "active": "False", "heatmap": 0, "icao": "null", "led": "11", "purpose": "off", "wxsrc": "none" },
        { "active": "True", "heatmap": 20, "icao": "ktiw", "led": "12", "purpose": "all", "wxsrc": "adds" },
        { "active": "False", "heatmap": 0, "icao": "null", "led": "13", "purpose": "off", "wxsrc": "none" },
        { "active": "True", "heatmap": 0, "icao": "ksea", "led": "14", "purpose": "all", "wxsrc": "adds" },
        { "active": "True", "heatmap": 8, "icao": "krnt", "led": "15", "purpose": "all", "wxsrc": "adds" },
        { "active": "True", "heatmap": 100, "icao": "kbfi", "led": "16", "purpose": "all", "wxsrc": "adds" },
        { "active": "False", "heatmap": 0, "icao": "null", "led": "17", "purpose": "off", "wxsrc": "none" },
        { "active": "True", "heatmap": 100, "icao": "kpwt", "led": "18", "purpose": "all", "wxsrc": "adds" },
        { "active": "False", "heatmap": 0, "icao": "null", "led": "19", "purpose": "off", "wxsrc": "none" },
        { "active": "True", "heatmap": 0, "icao": "kpae", "led": "20", "purpose": "all", "wxsrc": "adds" },
        { "active": "True", "heatmap": 15, "icao": "kawo", "led": "21", "purpose": "all", "wxsrc": "adds" },
        { "active": "False", "heatmap": 0, "icao": "null", "led": "22", "purpose": "off", "wxsrc": "none" },
        { "active": "True", "heatmap": 0, "icao": "k0s9", "led": "23", "purpose": "all", "wxsrc": "adds" },
        { "active": "True", "heatmap": 0, "icao": "knuw", "led": "24", "purpose": "all", "wxsrc": "adds" },
        { "active": "True", "heatmap": 20, "icao": "kbvs", "led": "25", "purpose": "all", "wxsrc": "adds" },
        { "active": "True", "heatmap": 3, "icao": "kbli", "led": "26", "purpose": "all", "wxsrc": "adds" },
        { "active": "True", "heatmap": 0, "icao": "kors", "led": "27", "purpose": "all", "wxsrc": "adds" },
        { "active": "True", "heatmap": 12, "icao": "kfhr", "led": "28", "purpose": "all", "wxsrc": "adds" },
        { "active": "False", "heatmap": 0, "icao": "null", "led": "29", "purpose": "off", "wxsrc": "none" },
        { "active": "True", "heatmap": 0, "icao": "kclm", "led": "30", "purpose": "all", "wxsrc": "adds" },
        { "active": "False", "heatmap": 0, "icao": "null", "led": "31", "purpose": "off", "wxsrc": "none" },
        { "active": "False", "heatmap": 0, "icao": "null", "led": "32", "purpose": "off", "wxsrc": "none" },
        { "active": "True", "heatmap": 0, "icao": "kuil", "led": "33", "purpose": "all", "wxsrc": "adds" },
        { "active": "False", "heatmap": 0, "icao": "null", "led": "34", "purpose": "off", "wxsrc": "none" },
        { "active": "False", "heatmap": 0, "icao": "null", "led": "35", "purpose": "off", "wxsrc": "none" },
        { "active": "False", "heatmap": 0, "icao": "null", "led": "36", "purpose": "off", "wxsrc": "none" },
        { "active": "False", "heatmap": 0, "icao": "null", "led": "37", "purpose": "off", "wxsrc": "none" },
        { "active": "True", "heatmap": 0, "icao": "khqm", "led": "38", "purpose": "all", "wxsrc": "adds" },
        { "active": "False", "heatmap": 0, "icao": "null", "led": "39", "purpose": "off", "wxsrc": "none" },
        { "active": "False", "heatmap": 0, "icao": "null", "led": "40", "purpose": "off", "wxsrc": "none" },
        { "active": "False", "heatmap": 0, "icao": "null", "led": "41", "purpose": "off", "wxsrc": "none" },
        { "active": "False", "heatmap": 0, "icao": "null", "led": "42", "purpose": "off", "wxsrc": "none" },
        { "active": "False", "heatmap": 0, "icao": "lgnd", "led": "43", "purpose": "all", "wxsrc": "vfr" },
        { "active": "False", "heatmap": 0, "icao": "lgnd", "led": "44", "purpose": "all", "wxsrc": "mvfr" },
        { "active": "False", "heatmap": 0, "icao": "lgnd", "led": "45", "purpose": "all", "wxsrc": "ifr" },
        { "active": "False", "heatmap": 0, "icao": "lgnd", "led": "46", "purpose": "all", "wxsrc": "lifr" },
        { "active": "False", "heatmap": 0, "icao": "lgnd", "led": "47", "purpose": "all", "wxsrc": "home" },
        { "active": "False", "heatmap": 0, "icao": "lgnd", "led": "48", "purpose": "all", "wxsrc": "unkn" },
        { "active": "False", "heatmap": 0, "icao": "lgnd", "led": "49", "purpose": "all", "wxsrc": "none" }
    ]
}
